linear_client.py
linear_search.py
ticket_search.py
linear_ticket_cli-1.0.0.dist-info/licenses/LICENSE
linear_ticket_cli-1.0.0.dist-info/METADATA
linear_ticket_cli-1.0.0.dist-info/WHEEL
linear_ticket_cli-1.0.0.dist-info/entry_points.txt
linear_ticket_cli-1.0.0.dist-info/top_level.txt
linear_ticket_cli-1.0.0.dist-info/RECORD
