Metadata-Version: 2.4
Name: linear-ticket-cli
Version: 1.0.0
Summary: A comprehensive command-line tool for managing Linear tickets with AI-agent friendly interfaces
Author-email: Davide Vittori <me@vittoridavid.com>
Maintainer-email: Davide Vittori <me@vittoridavid.com>
License: MIT License
Project-URL: Homepage, https://github.com/vittoridavide/linear-cli
Project-URL: Repository, https://github.com/vittoridavide/linear-cli
Project-URL: Issues, https://github.com/vittoridavide/linear-cli/issues
Project-URL: Documentation, https://github.com/vittoridavide/linear-cli#readme
Keywords: linear,cli,ticket-management,project-management,ai-agent,automation,graphql,productivity
Classifier: Development Status :: 5 - Production/Stable
Classifier: Intended Audience :: Developers
Classifier: Intended Audience :: System Administrators
Classifier: Operating System :: OS Independent
Classifier: Programming Language :: Python :: 3
Classifier: Programming Language :: Python :: 3.7
Classifier: Programming Language :: Python :: 3.8
Classifier: Programming Language :: Python :: 3.9
Classifier: Programming Language :: Python :: 3.10
Classifier: Programming Language :: Python :: 3.11
Classifier: Programming Language :: Python :: 3.12
Classifier: Topic :: Software Development :: Libraries :: Python Modules
Classifier: Topic :: System :: Systems Administration
Classifier: Topic :: Utilities
Classifier: Environment :: Console
Requires-Python: >=3.7
License-File: LICENSE
Requires-Dist: requests>=2.31.0
Requires-Dist: fuzzywuzzy>=0.18.0
Requires-Dist: python-levenshtein>=0.21.0
Provides-Extra: dev
Requires-Dist: pytest>=6.0; extra == "dev"
Requires-Dist: pytest-cov; extra == "dev"
Requires-Dist: black; extra == "dev"
Requires-Dist: flake8; extra == "dev"
Requires-Dist: mypy; extra == "dev"
Dynamic: license-file
